fabi_demo/__init__.py
fabi_demo/__init__.pyi
fabi_demo/cli.py
fabi_demo/cli.pyi
fabi_demo/fabi_demo.py
fabi_demo/fabi_demo.pyi
fabi_demo/version.py
fabi_demo/version.pyi
fabi_demo-1.0.7.dist-info/METADATA
fabi_demo-1.0.7.dist-info/WHEEL
fabi_demo-1.0.7.dist-info/entry_points.txt
fabi_demo-1.0.7.dist-info/top_level.txt
fabi_demo-1.0.7.dist-info/RECORD
