Metadata-Version: 2.4
Name: fabi-demo
Version: 1.0.7
Author-email: FZV <fake_email@email.com>
License: GNU GENERAL PUBLIC LICENSE
Classifier: Intended Audience :: Information Technology
Classifier: Intended Audience :: Science/Research
Classifier: License :: OSI Approved :: GNU General Public License v3 (GPLv3)
Classifier: Programming Language :: Python :: 3.8
Classifier: Programming Language :: Python :: 3.9
Classifier: Programming Language :: Python :: 3.10
Classifier: Programming Language :: Python :: 3.11
Classifier: Programming Language :: Python :: 3.12
Classifier: Topic :: Software Development :: Libraries :: Python Modules
Requires-Python: >=3.10
Requires-Dist: click<9.0.0,>=8.3.1
Requires-Dist: httpx<0.29.0,>=0.28.1
Requires-Dist: rich<15.0.0,>=14.2.0
Provides-Extra: dev
Requires-Dist: pre-commit; extra == "dev"
Provides-Extra: docs
Requires-Dist: Sphinx>=7.0; extra == "docs"
Requires-Dist: sphinx_rtd_theme; extra == "docs"
Requires-Dist: sphinx-copybutton; extra == "docs"
Requires-Dist: sphinx-tabs; extra == "docs"
Provides-Extra: tests
Requires-Dist: coverage>=6.4; extra == "tests"
Requires-Dist: coveralls>=3.3; extra == "tests"
Requires-Dist: pytest>=7.4; extra == "tests"
Requires-Dist: pytest-cov>=4.1; extra == "tests"
Requires-Dist: pytest-pep8>=1.0; extra == "tests"
Requires-Dist: pydocstyle>=4.0; extra == "tests"
Requires-Dist: isort>4.3; extra == "tests"
Requires-Dist: check-manifest>=0.40; extra == "tests"
Provides-Extra: all
Requires-Dist: fabi_demo[docs,tests]; extra == "all"
